setup.cfg
setup.py
jsvn_qa_utils_rest/__init__.py
jsvn_qa_utils_rest.egg-info/PKG-INFO
jsvn_qa_utils_rest.egg-info/SOURCES.txt
jsvn_qa_utils_rest.egg-info/dependency_links.txt
jsvn_qa_utils_rest.egg-info/top_level.txt
jsvn_qa_utils_rest/src/__init__.py
jsvn_qa_utils_rest/src/data.py
jsvn_qa_utils_rest/src/rest_client.py
jsvn_qa_utils_rest/src/validate.py