Metadata-Version: 2.1
Name: jsvn-qa-utils-rest
Version: 1.0.3
Summary: rest client with allure and cerberus
Home-page: https://github.com/JsvnSvn/jsvn_qa_utils_rest
Author: Jseven
Author-email: codejseven@gmail.com
License: MIT Licence
Platform: UNKNOWN
